odoo/addons/base_cron_exclusion/README.rst
odoo/addons/base_cron_exclusion/__init__.py
odoo/addons/base_cron_exclusion/__manifest__.py
odoo/addons/base_cron_exclusion/i18n/base_cron_exclusion.pot
odoo/addons/base_cron_exclusion/i18n/ca.po
odoo/addons/base_cron_exclusion/i18n/cs_CZ.po
odoo/addons/base_cron_exclusion/i18n/es.po
odoo/addons/base_cron_exclusion/i18n/es_AR.po
odoo/addons/base_cron_exclusion/i18n/fr.po
odoo/addons/base_cron_exclusion/i18n/it.po
odoo/addons/base_cron_exclusion/i18n/zh_CN.po
odoo/addons/base_cron_exclusion/models/__init__.py
odoo/addons/base_cron_exclusion/models/ir_cron.py
odoo/addons/base_cron_exclusion/readme/CONTRIBUTORS.rst
odoo/addons/base_cron_exclusion/readme/DESCRIPTION.rst
odoo/addons/base_cron_exclusion/readme/USAGE.rst
odoo/addons/base_cron_exclusion/static/description/icon.png
odoo/addons/base_cron_exclusion/static/description/index.html
odoo/addons/base_cron_exclusion/views/ir_cron_view.xml
odoo14_addon_base_cron_exclusion-14.0.1.0.1.dev9.dist-info/METADATA
odoo14_addon_base_cron_exclusion-14.0.1.0.1.dev9.dist-info/WHEEL
odoo14_addon_base_cron_exclusion-14.0.1.0.1.dev9.dist-info/top_level.txt
odoo14_addon_base_cron_exclusion-14.0.1.0.1.dev9.dist-info/RECORD
